cho/__init__.py
cho - Copy/__init__.py
cho - Copy/chocho.py
cho - Copy/col2fig.py
cho - Copy/hcho.py
cho - Copy/setup.py
cho - Copy (2)/__init__.py
cho - Copy (2)/chocho.py
cho - Copy (2)/col2fig.py
cho - Copy (2)/hcho.py
cho - Copy (2)/setup.py
cho-0.0.10.dist-info/METADATA
cho-0.0.10.dist-info/WHEEL
cho-0.0.10.dist-info/top_level.txt
cho-0.0.10.dist-info/RECORD
