Metadata-Version: 2.1
Name: cho
Version: 0.0.10
Summary: left blank
Home-page: https://github.com/soonyenju/cho
Author: Songyan Zhu
Author-email: soonyenju@foxmail.com
License: MIT Licence
Keywords: hcho,chocho
Platform: any
